setup.py
hdf5pickle/__init__.py
hdf5pickle/base.py
hdf5pickle.egg-info/PKG-INFO
hdf5pickle.egg-info/SOURCES.txt
hdf5pickle.egg-info/dependency_links.txt
hdf5pickle.egg-info/not-zip-safe
hdf5pickle.egg-info/requires.txt
hdf5pickle.egg-info/top_level.txt