Metadata-Version: 1.0
Name: hdf5pickle
Version: 0.3
Summary: Pickle Python objects to HDF5 files
Home-page: https://github.com/rmcgibbo/hdf5pickle
Author: Robert McGibbon
Author-email: rmcgibbo@gmail.com
License: BSD & Python Software Foundation License
Keywords: hdf5 pickle pytables
Platform: UNKNOWN
